MasteringElasticsearchZhongwenban/README.md
MasteringElasticsearchZhongwenban/__init__.py
MasteringElasticsearchZhongwenban/__main__.py
MasteringElasticsearchZhongwenban/file.epub
MasteringElasticsearchZhongwenban/index.html
MasteringElasticsearchZhongwenban/css/__init__.py
MasteringElasticsearchZhongwenban/css/annotations.css
MasteringElasticsearchZhongwenban/css/main.css
MasteringElasticsearchZhongwenban/css/normalize.css
MasteringElasticsearchZhongwenban/css/popup.css
MasteringElasticsearchZhongwenban/font/__init__.py
MasteringElasticsearchZhongwenban/font/fontello.eot
MasteringElasticsearchZhongwenban/font/fontello.svg
MasteringElasticsearchZhongwenban/font/fontello.ttf
MasteringElasticsearchZhongwenban/font/fontello.woff
MasteringElasticsearchZhongwenban/img/__init__.py
MasteringElasticsearchZhongwenban/img/annotator-glyph-sprite.png
MasteringElasticsearchZhongwenban/img/annotator-icon-sprite.png
MasteringElasticsearchZhongwenban/img/apple-touch-icon.png
MasteringElasticsearchZhongwenban/img/cancelfullscreen.png
MasteringElasticsearchZhongwenban/img/close.png
MasteringElasticsearchZhongwenban/img/fullscreen.png
MasteringElasticsearchZhongwenban/img/loader.gif
MasteringElasticsearchZhongwenban/img/menu-icon.png
MasteringElasticsearchZhongwenban/img/save.png
MasteringElasticsearchZhongwenban/img/saved.png
MasteringElasticsearchZhongwenban/img/settings-s.png
MasteringElasticsearchZhongwenban/img/settings.png
MasteringElasticsearchZhongwenban/img/star.png
MasteringElasticsearchZhongwenban/js/__init__.py
MasteringElasticsearchZhongwenban/js/epub.js
MasteringElasticsearchZhongwenban/js/epub.min.js
MasteringElasticsearchZhongwenban/js/epub.min.map
MasteringElasticsearchZhongwenban/js/hooks.min.js
MasteringElasticsearchZhongwenban/js/hooks.min.map
MasteringElasticsearchZhongwenban/js/reader.js
MasteringElasticsearchZhongwenban/js/reader.js.map
MasteringElasticsearchZhongwenban/js/reader.min.js
MasteringElasticsearchZhongwenban/js/reader.min.map
mastering_elasticsearch_zhongwenban-2024.2.29.0.dist-info/METADATA
mastering_elasticsearch_zhongwenban-2024.2.29.0.dist-info/WHEEL
mastering_elasticsearch_zhongwenban-2024.2.29.0.dist-info/entry_points.txt
mastering_elasticsearch_zhongwenban-2024.2.29.0.dist-info/top_level.txt
mastering_elasticsearch_zhongwenban-2024.2.29.0.dist-info/RECORD
